Metadata-Version: 1.1
Name: gwr
Version: 1.0.1
Summary: geographically weighted regression
Home-page: https://github.com/TaylorOshan/gwr
Author: Taylor M. Oshan
Author-email: tayoshan@gmail.com
License: 3-Clause BSD
Keywords: spatial statistics
Platform: UNKNOWN
Classifier: Development Status :: 5 - Production/Stable
Classifier: Intended Audience :: Science/Research
Classifier: Intended Audience :: Developers
Classifier: Intended Audience :: Education
Classifier: Topic :: Scientific/Engineering
Classifier: Topic :: Scientific/Engineering :: GIS
Classifier: License :: OSI Approved :: BSD License
Classifier: Programming Language :: Python
Classifier: Programming Language :: Python :: 2.5
Classifier: Programming Language :: Python :: 2.6
Classifier: Programming Language :: Python :: 2.7
Classifier: Programming Language :: Python :: 3.4
